_ordereddict.pyd
ruamel.ordereddict-0.4.15-py2.7-nspkg.pth
ruamel/ordereddict/__init__.py
ruamel.ordereddict-0.4.15.dist-info/LICENSE
ruamel.ordereddict-0.4.15.dist-info/METADATA
ruamel.ordereddict-0.4.15.dist-info/WHEEL
ruamel.ordereddict-0.4.15.dist-info/namespace_packages.txt
ruamel.ordereddict-0.4.15.dist-info/top_level.txt
ruamel.ordereddict-0.4.15.dist-info/RECORD
