Metadata-Version: 2.1
Name: ruamel.ordereddict
Version: 0.4.15
Summary: a version of dict that keeps keys in insertion resp. sorted order
Home-page: https://bitbucket.org/ruamel/ordereddict
Author: Anthon van der Neut
Author-email: a.van.der.neut@ruamel.eu
License: MIT license
Platform: UNKNOWN
Classifier: Development Status :: 5 - Production/Stable
Classifier: Intended Audience :: System Administrators
Classifier: License :: OSI Approved :: MIT License
Classifier: Operating System :: POSIX :: Linux
Classifier: Programming Language :: Python
